{
 "baseUrl":"support/slwebview_files",
 "homeHid":1,
 "initialElement":"",
 "sections":[
  {
   "hid":1,
   "sid":"grading",
   "name":"grading",
   "fullname":"grading",
   "label":"grading",
   "parent":0,
   "descendants":[
    2,
    3,
    4,
    5,
    6
   ],
   "hierarchyUrl":"support/slwebview_files/grading_h_1.json",
   "backingUrl":"support/slwebview_files/grading_m.json"
  }
 ],
 "optViews":[
 ],
 "display":{
  "informer":false
 },
 "iconsUrl":"support/slwebview_files/grading_icons.css"
}